limioptic/__init__.py
limioptic/__main__.py
limioptic/_compile_linux.sh
limioptic/_compile_win.bat
limioptic/_update.py
limioptic/climioptic.cpp
limioptic/climioptic.h
limioptic/climioptic.o
limioptic/graphics.py
limioptic/helper.py
limioptic/importsrc.py
limioptic/libgcc_s_dw2-1.dll
limioptic/liblimioptic-linux.so
limioptic/liblimioptic-win.so
limioptic/libstdc++-6.dll
limioptic/limioptic.cpp
limioptic/limioptic.h
limioptic/limioptic.o
limioptic/limioptic_calc.py
limioptic/logo.png
limioptic/msvcp90.dll
limioptic/plotBeamEmittance.pyw
limioptic/plotBeamProfile.pyw
limioptic/run.py
limioptic/syntax.py
limioptic/update.txt
limioptic/user_functions.py
limioptic-0.1.1.dist-info/entry_points.txt
limioptic-0.1.1.dist-info/WHEEL
limioptic-0.1.1.dist-info/METADATA
limioptic-0.1.1.dist-info/RECORD
